README.md
setup.py
nwrap/__init__.py
nwrap.egg-info/PKG-INFO
nwrap.egg-info/SOURCES.txt
nwrap.egg-info/dependency_links.txt
nwrap.egg-info/entry_points.txt
nwrap.egg-info/top_level.txt